bepospliz/__init__.py
bepospliz/bepospliz.py
bepospliz-1.0.1.dist-info/LICENSE
bepospliz-1.0.1.dist-info/METADATA
bepospliz-1.0.1.dist-info/WHEEL
bepospliz-1.0.1.dist-info/top_level.txt
bepospliz-1.0.1.dist-info/RECORD
