Metadata-Version: 2.1
Name: bepospliz
Version: 1.0.1
Summary: BePosPliz (be positional please) is a lightweight module to anonymize the arguments of a function.
Home-page: https://github.com/qexat/bepospliz
Author: Qexat
Author-email: 43090614+qexat@users.noreply.github.com
License: MIT
Classifier: License :: OSI Approved :: MIT License
Classifier: Programming Language :: Python :: 3
Classifier: Programming Language :: Python :: 3 :: Only
Classifier: Programming Language :: Python :: Implementation :: CPython
Classifier: Programming Language :: Python :: Implementation :: PyPy
Requires-Python: >=3.11
License-File: LICENSE
